hypertiling/__init__.py
hypertiling/arithmetics.py
hypertiling/arraytransformation.py
hypertiling/check_numba.py
hypertiling/core.py
hypertiling/distance.py
hypertiling/geodesics.py
hypertiling/ion.py
hypertiling/kernel_abc.py
hypertiling/neighbors.py
hypertiling/operators.py
hypertiling/representations.py
hypertiling/transformation.py
hypertiling/util.py
hypertiling/experimental/__init__.py
hypertiling/experimental/boundary.py
hypertiling/experimental/excelwriter.py
hypertiling/experimental/stability.py
hypertiling/graphics/__init__.py
hypertiling/graphics/animation.py
hypertiling/graphics/plot.py
hypertiling/graphics/svg.py
hypertiling/kernel/DUN07.py
hypertiling/kernel/DUN07X.py
hypertiling/kernel/DUN86.py
hypertiling/kernel/GR.py
hypertiling/kernel/GRC.py
hypertiling/kernel/GRCT.py
hypertiling/kernel/GRCT_util.py
hypertiling/kernel/GRC_util.py
hypertiling/kernel/GRG.py
hypertiling/kernel/GRGS.py
hypertiling/kernel/GRGS_util.py
hypertiling/kernel/GRG_util.py
hypertiling/kernel/GR_util.py
hypertiling/kernel/SRG.py
hypertiling/kernel/SRG_util.py
hypertiling/kernel/SRL.py
hypertiling/kernel/SRL_util.py
hypertiling/kernel/SRS.py
hypertiling/kernel/SR_base.py
hypertiling/kernel/SR_util.py
hypertiling/kernel/__init__.py
hypertiling/kernel/hyperpolygon.py
hypertiling-1.4.1.dist-info/licenses/LICENSE.txt
hypertiling-1.4.1.dist-info/METADATA
hypertiling-1.4.1.dist-info/WHEEL
hypertiling-1.4.1.dist-info/top_level.txt
hypertiling-1.4.1.dist-info/RECORD
