Metadata-Version: 2.4
Name: hypertiling
Version: 1.4.1
Summary: hypertiling is a high-performance Python library for the generation and visualization of regular hyperbolic lattices
Author: Manuel Schrauth, Yanick Thurn, Florian Goth, Jefferson S. E. Portela, Dietmar Herdt, Felix Dusel
Maintainer: Manuel Schrauth, Yanick Thurn, Florian Goth, Jefferson S. E. Portela, Dietmar Herdt, Felix Dusel
Requires-Python: >=3.5
License-File: LICENSE.txt
Requires-Dist: numpy
Requires-Dist: matplotlib
Requires-Dist: networkx
Requires-Dist: setuptools
Requires-Dist: sortedcontainers
Requires-Dist: scipy
Requires-Dist: ipython
Provides-Extra: numba
Requires-Dist: numba; extra == "numba"
Provides-Extra: dev
Requires-Dist: black; extra == "dev"
Requires-Dist: radon; extra == "dev"
Provides-Extra: test
Requires-Dist: pytest; extra == "test"
Requires-Dist: pytest-cov; extra == "test"
Requires-Dist: coverage[toml]; extra == "test"
Provides-Extra: doc
Requires-Dist: sphinx; extra == "doc"
Dynamic: license-file
